neuro_canvas/__init__.py
neuro_canvas/__main__.py
neuro_canvas/actions.py
neuro_canvas/application.py
neuro_canvas/canvas.py
neuro_canvas/constants.py
neuro_canvas-0.4.1.dist-info/LICENSE
neuro_canvas-0.4.1.dist-info/METADATA
neuro_canvas-0.4.1.dist-info/WHEEL
neuro_canvas-0.4.1.dist-info/entry_points.txt
neuro_canvas-0.4.1.dist-info/top_level.txt
neuro_canvas-0.4.1.dist-info/RECORD
