Metadata-Version: 2.2
Name: neuro-canvas
Version: 0.4.1
Summary: Neuro's Canvas - A drawing application
Author: Kaya-Kaya
License: MIT
Project-URL: Source, https://github.com/Kaya-Kaya/neuro_canvas
Project-URL: Bug Tracker, https://github.com/Kaya-Kaya/neuro_canvas/issues
Classifier: Programming Language :: Python :: 3
Classifier: License :: OSI Approved :: MIT License
Classifier: Operating System :: OS Independent
Requires-Python: >=3.9
License-File: LICENSE
Requires-Dist: neuro_api~=1.0
Requires-Dist: pygame~=2.6
Requires-Dist: jsonschema~=4.23
